swarmauri_certs_csronly/CsrOnlyService.py
swarmauri_certs_csronly/__init__.py
swarmauri_certs_csronly-0.8.0.dev4.dist-info/LICENSE
swarmauri_certs_csronly-0.8.0.dev4.dist-info/METADATA
swarmauri_certs_csronly-0.8.0.dev4.dist-info/WHEEL
swarmauri_certs_csronly-0.8.0.dev4.dist-info/entry_points.txt
swarmauri_certs_csronly-0.8.0.dev4.dist-info/RECORD
